{
    "1": {
        "price": "4990",
        "title": "Burger"
    },
    "2": {
        "price": "1490",
        "title": "Fries"
    },
    "3": {
        "price": "3490",
        "title": "Hotdog"
    },
    "4": {
        "price": "3990",
        "title": "Taco"
    },
    "5": {
        "price": "7990",
        "title": "Pizza"
    },
    "6": {
        "price": "1490",
        "title": "Donut"
    },
    "7": {
        "price": "1990",
        "title": "Popcorn"
    },
    "8": {
        "price": "1490",
        "title": "Coke"
    },
    "9": {
        "price": "10990",
        "title": "Cake"
    },
    "10": {
        "price": "5990",
        "title": "Icecream"
    },
    "11": {
        "price": "3990",
        "title": "Cookie"
    },
    "12": {
        "price": "7990",
        "title": "Flan"
    }
}